{
  "id": "tech_stack",
  "type": "SharedSlice",
  "name": "TechStack",
  "description": "TechStack",
  "variations": [
    {
      "id": "default",
      "name": "Default",
      "docURL": "...",
      "version": "initial",
      "description": "Default",
      "imageUrl": "",
      "primary": {
        "heading": {
          "type": "Text",
          "config": {
            "label": "Heading",
            "placeholder": ""
          }
        },
        "technologies": {
          "type": "Group",
          "config": {
            "label": "Technologies",
            "repeat": true,
            "fields": {
              "name": {
                "type": "Text",
                "config": {
                  "label": "Name",
                  "placeholder": ""
                }
              },
              "color": {
                "type": "Color",
                "config": {
                  "label": "Color",
                  "placeholder": ""
                }
              }
            }
          }
        }
      },
      "items": {}
    }
  ]
}